harlequelrah_py/__init__.py
harlequelrah_py/utilitaire.py
harlequelrah_py/date/__init__.py
harlequelrah_py/date/clock.py
harlequelrah_py/files/__init__.py
harlequelrah_py/files/myfiles.py
harlequelrah_py/integer/__init__.py
harlequelrah_py/integer/base_converter.py
harlequelrah_py/integer/math_primes.py
harlequelrah_py/integer/math_utils.py
harlequelrah_py/integer/myint.py
harlequelrah_py/string/__init__.py
harlequelrah_py/string/mychar.py
harlequelrah_py/string/mycryptography.py
harlequelrah_py/string/mysequence.py
harlequelrah_py/turtle/__init__.py
harlequelrah_py/turtle/geometric_shape.py
harlequelrah_py/turtle/myturtle.py
harlequelrah_py/turtle/particular_shape.py
harlequelrah_py-0.1.4.dist-info/METADATA
harlequelrah_py-0.1.4.dist-info/WHEEL
harlequelrah_py-0.1.4.dist-info/top_level.txt
harlequelrah_py-0.1.4.dist-info/RECORD
