Metadata-Version: 2.1
Name: harlequelrah_py
Version: 0.1.4
Summary: Package personnalisé pour faciliter la programmation et le développement avec python
Home-page: https://github.com/Harlequelrah/Library-harlequelrah_py
Author: Harlequelrah
Author-email: maximeatsoudegbovi@example.com
Classifier: Programming Language :: Python :: 3
Classifier: License :: OSI Approved :: GNU Lesser General Public License v3 (LGPLv3)
Classifier: Operating System :: OS Independent
Requires-Python: >=3.10
Requires-Dist: numpy >=1.18.0
Requires-Dist: turtle
Requires-Dist: python-dateutil
